dapp_manager/__init__.py
dapp_manager/__main__.py
dapp_manager/autocomplete/__init__.py
dapp_manager/autocomplete/scripts/.dapp-manager.bash
dapp_manager/autocomplete/scripts/.dapp-manager.fish
dapp_manager/autocomplete/scripts/.dapp-manager.zsh
dapp_manager/cli.py
dapp_manager/dapp_manager.py
dapp_manager/dapp_starter.py
dapp_manager/exceptions.py
dapp_manager/inspect/__init__.py
dapp_manager/inspect/__main__.py
dapp_manager/inspect/templates/app_structure/network.txt
dapp_manager/inspect/templates/app_structure/node.txt
dapp_manager/inspect/templates/app_structure/payload.txt
dapp_manager/inspect/templates/app_structure.txt
dapp_manager/py.typed
dapp_manager/storage.py
dapp_stats/README.md
dapp_stats/__init__.py
dapp_stats/__main__.py
dapp_stats/dapp_size_resolver.py
dapp_stats/dapp_stats.py
dapp_stats/exceptions.py
dapp_stats/statistics/__init__.py
dapp_stats/statistics/enums.py
dapp_stats/statistics/models.py
dapp_stats/statistics/schemas.py
dapp_manager-0.3.0.dist-info/LICENSE
dapp_manager-0.3.0.dist-info/METADATA
dapp_manager-0.3.0.dist-info/WHEEL
dapp_manager-0.3.0.dist-info/entry_points.txt
dapp_manager-0.3.0.dist-info/RECORD
