Metadata-Version: 2.1
Name: dapp-manager
Version: 0.3.0
Summary: Golem dapp-manager - run decetralized apps on the Golem Network using a 'docker-compose'-like interface
Home-page: https://github.com/golemfactory/dapp-manager
License: LGPL-3.0
Author: Golem Factory
Author-email: contact@golem.network
Requires-Python: >=3.8,<4.0
Classifier: Development Status :: 2 - Pre-Alpha
Classifier: Environment :: Console
Classifier: Intended Audience :: Developers
Classifier: License :: OSI Approved :: GNU Lesser General Public License v3 (LGPLv3)
Classifier: Natural Language :: English
Classifier: Programming Language :: Python :: 3
Classifier: Programming Language :: Python :: 3.8
Classifier: Programming Language :: Python :: 3.9
Classifier: Programming Language :: Python :: 3.10
Classifier: Programming Language :: Python :: 3.11
Classifier: Topic :: Software Development
Classifier: Topic :: System :: Distributed Computing
Requires-Dist: appdirs (>=1.4,<2.0)
Requires-Dist: click (>=7.0,<8.0)
Requires-Dist: dapp-runner (>=0.3,<0.4)
Requires-Dist: mako (>=1.2.4,<2.0.0)
Requires-Dist: psutil (>=5.9,<6.0)
Requires-Dist: pydantic (>=1.9,<2.0)
Requires-Dist: requests (>=2.31.0,<3.0.0)
Project-URL: Repository, https://github.com/golemfactory/dapp-manager
